roxie_3ml/__init__.py
roxie_3ml/assets/MMBSE_Favicon_Color.png
roxie_3ml/assets/icons/activity.svg
roxie_3ml/assets/icons/airplay.svg
roxie_3ml/assets/icons/alert-circle.svg
roxie_3ml/assets/icons/alert-octagon.svg
roxie_3ml/assets/icons/alert-triangle.svg
roxie_3ml/assets/icons/align-center.svg
roxie_3ml/assets/icons/align-justify.svg
roxie_3ml/assets/icons/align-left.svg
roxie_3ml/assets/icons/align-right.svg
roxie_3ml/assets/icons/anchor.svg
roxie_3ml/assets/icons/aperture.svg
roxie_3ml/assets/icons/archive.svg
roxie_3ml/assets/icons/arrow-down-circle.svg
roxie_3ml/assets/icons/arrow-down-left.svg
roxie_3ml/assets/icons/arrow-down-right.svg
roxie_3ml/assets/icons/arrow-down.svg
roxie_3ml/assets/icons/arrow-left-circle.svg
roxie_3ml/assets/icons/arrow-left.svg
roxie_3ml/assets/icons/arrow-right-circle.svg
roxie_3ml/assets/icons/arrow-right.svg
roxie_3ml/assets/icons/arrow-up-circle.svg
roxie_3ml/assets/icons/arrow-up-left.svg
roxie_3ml/assets/icons/arrow-up-right.svg
roxie_3ml/assets/icons/arrow-up.svg
roxie_3ml/assets/icons/at-sign.svg
roxie_3ml/assets/icons/award.svg
roxie_3ml/assets/icons/bar-chart-2.svg
roxie_3ml/assets/icons/bar-chart.svg
roxie_3ml/assets/icons/battery-charging.svg
roxie_3ml/assets/icons/battery.svg
roxie_3ml/assets/icons/bell-off.svg
roxie_3ml/assets/icons/bell.svg
roxie_3ml/assets/icons/bluetooth.svg
roxie_3ml/assets/icons/bold.svg
roxie_3ml/assets/icons/book-open.svg
roxie_3ml/assets/icons/book.svg
roxie_3ml/assets/icons/bookmark.svg
roxie_3ml/assets/icons/box.svg
roxie_3ml/assets/icons/briefcase.svg
roxie_3ml/assets/icons/calendar.svg
roxie_3ml/assets/icons/camera-off.svg
roxie_3ml/assets/icons/camera.svg
roxie_3ml/assets/icons/cast.svg
roxie_3ml/assets/icons/check-circle.svg
roxie_3ml/assets/icons/check-square.svg
roxie_3ml/assets/icons/check.svg
roxie_3ml/assets/icons/chevron-down.svg
roxie_3ml/assets/icons/chevron-left.svg
roxie_3ml/assets/icons/chevron-right.svg
roxie_3ml/assets/icons/chevron-up.svg
roxie_3ml-1.1.1.dist-info/LICENSES/GPL-3.0-or-later.txt
roxie_3ml-1.1.1.dist-info/LICENSES/LicenseRef-feather-MIT.txt
roxie_3ml-1.1.1.dist-info/METADATA
roxie_3ml-1.1.1.dist-info/WHEEL
roxie_3ml-1.1.1.dist-info/entry_points.txt
roxie_3ml-1.1.1.dist-info/RECORD
